mldatatools/__init__.py
mldatatools-0.0.2.dist-info/LICENSE
mldatatools-0.0.2.dist-info/METADATA
mldatatools-0.0.2.dist-info/WHEEL
mldatatools-0.0.2.dist-info/top_level.txt
mldatatools-0.0.2.dist-info/RECORD
